util_rc/__init__.py
util_rc/main.py
util_rc-0.2.7.dist-info/METADATA
util_rc-0.2.7.dist-info/WHEEL
util_rc-0.2.7.dist-info/top_level.txt
util_rc-0.2.7.dist-info/RECORD
