Metadata-Version: 2.1
Name: util-rc
Version: 0.2.7
Summary: A PyPI package to model risky choice
Author-email: Donna Ma <donna.ma@example.com>
Classifier: Programming Language :: Python :: 3
Classifier: License :: OSI Approved :: MIT License
Classifier: Operating System :: OS Independent
Requires-Python: >=3.8
Requires-Dist: numpy>=1.26.4
Requires-Dist: scipy>=1.12.0
